pymca_zocalo/__init__.py
pymca_zocalo/internals.py
pymca_zocalo/pymca_fitter.py
pymca_zocalo-0.2.0.dist-info/LICENSE
pymca_zocalo-0.2.0.dist-info/METADATA
pymca_zocalo-0.2.0.dist-info/WHEEL
pymca_zocalo-0.2.0.dist-info/entry_points.txt
pymca_zocalo-0.2.0.dist-info/top_level.txt
pymca_zocalo-0.2.0.dist-info/RECORD
