Metadata-Version: 2.1
Name: pymca-zocalo
Version: 0.2.0
Summary: PyMca components for automated data processing with Zocalo at Diamond Light Source
Home-page: https://github.com/DiamondLightSource/python-zocalo-pymca
Author: Tom Schoonjans
Author-email: Tom.Schoonjans@diamond.ac.uk
License: BSD license
Platform: UNKNOWN
Classifier: Development Status :: 3 - Alpha
Classifier: Intended Audience :: Developers
Classifier: License :: OSI Approved :: BSD License
Classifier: Natural Language :: English
Classifier: Operating System :: POSIX :: Linux
Classifier: Programming Language :: Python :: 3.6
Classifier: Programming Language :: Python :: 3.7
Classifier: Programming Language :: Python :: 3.8
Requires-Dist: workflows (>=1.7)
Requires-Dist: zocalo
Requires-Dist: setuptools
Requires-Dist: PyMca5
